infiray_irg-1.6.0.dist-info/METADATA
infiray_irg-1.6.0.dist-info/WHEEL
infiray_irg-1.6.0.dist-info/entry_points.txt
infiray_irg-1.6.0.dist-info/licenses/LICENSE
infiray_irg.py
infiray_irg-1.6.0.dist-info/RECORD
