Metadata-Version: 2.1
Name: infiray_irg
Version: 1.6.0
Summary: A simple parser for Infiray IRG radiometric thermal imaging files
Author-Email: jaseg <code@jaseg.de>
Classifier: Programming Language :: Python :: 3
Classifier: License :: OSI Approved :: MIT License
Classifier: Operating System :: OS Independent
Project-URL: Homepage, https://jaseg.de/project/infiray_irg
Project-URL: Issues, https://github.com/jaseg/infiray_irg/issues
Requires-Python: >=3.8
